{
  "date": "2026-04-20",
  "timestamp": "2026-04-20T21:03:55.308728+00:00",
  "megacaps": {
    "AAPL": {
      "price": 273.05,
      "daily_change": 1.04,
      "volume": 34667241
    },
    "MSFT": {
      "price": 418.07,
      "daily_change": -1.12,
      "volume": 27240190
    },
    "GOOGL": {
      "price": 337.42,
      "daily_change": -1.25,
      "volume": 18677899
    },
    "AMZN": {
      "price": 248.28,
      "daily_change": -0.91,
      "volume": 36557790
    },
    "NVDA": {
      "price": 202.06,
      "daily_change": 0.19,
      "volume": 118513377
    },
    "TSLA": {
      "price": 392.5,
      "daily_change": -2.03,
      "volume": 64190600
    },
    "META": {
      "price": 670.91,
      "daily_change": -2.56,
      "volume": 12357266
    },
    "BRK-B": {
      "price": 472.08,
      "daily_change": -0.53,
      "volume": 5091150
    }
  },
  "indices": {
    "SPY": {
      "price": 708.72,
      "daily_change": -0.2,
      "volume": 41604668
    },
    "QQQ": {
      "price": 646.79,
      "daily_change": -0.32,
      "volume": 36858900
    },
    "IWM": {
      "price": 277.35,
      "daily_change": 0.57,
      "volume": 22839069
    },
    "VTI": {
      "price": 350.21,
      "daily_change": -0.09,
      "volume": 3986163
    }
  },
  "sectors": {
    "XLK": {
      "price": 154.56,
      "daily_change": 0.14,
      "volume": 8061807
    },
    "XLF": {
      "price": 52.63,
      "daily_change": 0.38,
      "volume": 25055571
    },
    "XLE": {
      "price": 55.07,
      "daily_change": 0.09,
      "volume": 35073170
    },
    "XLV": {
      "price": 147.42,
      "daily_change": -0.93,
      "volume": 6321138
    },
    "XLI": {
      "price": 173.9,
      "daily_change": 0.22,
      "volume": 5715680
    }
  },
  "market_mood": "NEUTRAL",
  "small_vs_large_cap": "SMALL_CAPS_OUTPERFORMING"
}