{
  "date": "2025-11-17",
  "timestamp": "2025-11-17T20:35:41.752888+00:00",
  "megacaps": {
    "AAPL": {
      "price": 266.43,
      "daily_change": -2.19,
      "volume": 28314525
    },
    "MSFT": {
      "price": 506.78,
      "daily_change": -0.67,
      "volume": 9960959
    },
    "GOOGL": {
      "price": 284.93,
      "daily_change": 3.08,
      "volume": 42456643
    },
    "AMZN": {
      "price": 231.85,
      "daily_change": -1.21,
      "volume": 49007565
    },
    "NVDA": {
      "price": 185.14,
      "daily_change": -2.65,
      "volume": 136264321
    },
    "TSLA": {
      "price": 406.68,
      "daily_change": 0.58,
      "volume": 91062870
    },
    "META": {
      "price": 596.98,
      "daily_change": -2.05,
      "volume": 12309168
    },
    "BRK-B": {
      "price": 504.5,
      "daily_change": -0.87,
      "volume": 3146655
    }
  },
  "indices": {
    "SPY": {
      "price": 663.86,
      "daily_change": -1.2,
      "volume": 68098257
    },
    "QQQ": {
      "price": 601.39,
      "daily_change": -1.23,
      "volume": 53234099
    },
    "IWM": {
      "price": 232.33,
      "daily_change": -2.17,
      "volume": 46659890
    },
    "VTI": {
      "price": 325.6,
      "daily_change": -1.29,
      "volume": 3696296
    }
  },
  "sectors": {
    "XLK": {
      "price": 282.26,
      "daily_change": -2.04,
      "volume": 10500653
    },
    "XLF": {
      "price": 51.42,
      "daily_change": -1.95,
      "volume": 47683253
    },
    "XLE": {
      "price": 90.29,
      "daily_change": -1.88,
      "volume": 14007000
    },
    "XLV": {
      "price": 151.65,
      "daily_change": -0.12,
      "volume": 15001087
    },
    "XLI": {
      "price": 150.32,
      "daily_change": -1.11,
      "volume": 12465308
    }
  },
  "market_mood": "NEUTRAL",
  "small_vs_large_cap": "LARGE_CAPS_OUTPERFORMING"
}