{
  "date": "2026-05-20",
  "timestamp": "2026-05-20T22:04:34.074184+00:00",
  "megacaps": {
    "AAPL": {
      "price": 302.25,
      "daily_change": 1.1,
      "volume": 37276629
    },
    "MSFT": {
      "price": 421.06,
      "daily_change": 0.87,
      "volume": 27738933
    },
    "GOOGL": {
      "price": 388.91,
      "daily_change": 0.32,
      "volume": 30405838
    },
    "AMZN": {
      "price": 265.01,
      "daily_change": 2.19,
      "volume": 34425988
    },
    "NVDA": {
      "price": 223.47,
      "daily_change": 1.3,
      "volume": 171145403
    },
    "TSLA": {
      "price": 417.26,
      "daily_change": 3.25,
      "volume": 44903311
    },
    "META": {
      "price": 605.06,
      "daily_change": 0.41,
      "volume": 11270062
    },
    "BRK-B": {
      "price": 480.9,
      "daily_change": 0.09,
      "volume": 3302758
    }
  },
  "indices": {
    "SPY": {
      "price": 741.25,
      "daily_change": 1.02,
      "volume": 45085124
    },
    "QQQ": {
      "price": 713.15,
      "daily_change": 1.66,
      "volume": 35933262
    },
    "IWM": {
      "price": 279.87,
      "daily_change": 2.52,
      "volume": 31045643
    },
    "VTI": {
      "price": 364.19,
      "daily_change": 1.15,
      "volume": 3061513
    }
  },
  "sectors": {
    "XLK": {
      "price": 177.14,
      "daily_change": 2.25,
      "volume": 12594706
    },
    "XLF": {
      "price": 51.66,
      "daily_change": 1.1,
      "volume": 42136935
    },
    "XLE": {
      "price": 59.8,
      "daily_change": -2.43,
      "volume": 58965584
    },
    "XLV": {
      "price": 147.13,
      "daily_change": -0.13,
      "volume": 10503628
    },
    "XLI": {
      "price": 170.73,
      "daily_change": 1.18,
      "volume": 10492145
    }
  },
  "market_mood": "BULLISH",
  "small_vs_large_cap": "SMALL_CAPS_OUTPERFORMING"
}